sumo_output_parsers/__init__.py
sumo_output_parsers/csv_based_parser/__init__.py
sumo_output_parsers/csv_based_parser/collision_parser.py
sumo_output_parsers/csv_based_parser/statistic_parser.py
sumo_output_parsers/csv_based_parser/summary_parser.py
sumo_output_parsers/definition_parser/__init__.py
sumo_output_parsers/definition_parser/detectors_det_parser.py
sumo_output_parsers/logger_unit.py
sumo_output_parsers/models/__init__.py
sumo_output_parsers/models/matrix.py
sumo_output_parsers/models/parser.py
sumo_output_parsers/models/statics.py
sumo_output_parsers/tree_parser/__init__.py
sumo_output_parsers/tree_parser/fcd_parser.py
sumo_output_parsers/tree_parser/loop_detector_parser.py
sumo_output_parsers/visualizer/__init__.py
sumo_output_parsers/visualizer/detector_positions.py
sumo_output_parsers/visualizer/route_visualizer.py
sumo_output_parsers/visualizer/traffic_animation.py
sumo_output_parsers-0.61.dist-info/entry_points.txt
sumo_output_parsers-0.61.dist-info/WHEEL
sumo_output_parsers-0.61.dist-info/METADATA
sumo_output_parsers-0.61.dist-info/RECORD
