Metadata-Version: 2.1
Name: sumo-output-parsers
Version: 0.61
Summary: Fast and lightweight file parsers for SUMO(traffic simulator) output
License: MIT
Author: Kensuke Mitsuzawa
Author-email: kensuke.mit@gmail.com
Maintainer: Kensuke Mitsuzawa
Maintainer-email: kensuke.mit@gmail.com
Requires-Python: >=3.7,<3.10
Classifier: License :: OSI Approved :: MIT License
Classifier: Programming Language :: Python :: 3
Classifier: Programming Language :: Python :: 3.7
Classifier: Programming Language :: Python :: 3.8
Classifier: Programming Language :: Python :: 3.9
Provides-Extra: full
Requires-Dist: Cython
Requires-Dist: Shapely (>=1.7.0,<2.0.0); extra == "full"
Requires-Dist: SumoNetVis (>=1.6.0,<2.0.0); extra == "full"
Requires-Dist: adjustText; extra == "full"
Requires-Dist: dataclasses
Requires-Dist: geopandas (>=0.10.0,<0.11.0); extra == "full"
Requires-Dist: geoviews (>=1.9.1,<2.0.0); extra == "full"
Requires-Dist: h5py (>=3.1.0,<4.0.0)
Requires-Dist: hvplot (>=0.7.3,<0.8.0); extra == "full"
Requires-Dist: imageio-ffmpeg; extra == "full"
Requires-Dist: joblib
Requires-Dist: lxml
Requires-Dist: more_itertools
Requires-Dist: moviepy (<1.0.2); extra == "full"
Requires-Dist: nptyping (>=1.4.1,<2.0.0)
Requires-Dist: numpy (>=1.19.2,<2.0.0)
Requires-Dist: pandas (>=1.1.3,<2.0.0)
Requires-Dist: pyproj (>=3.0.0,<4.0.0); extra == "full"
Requires-Dist: pyviz; extra == "full"
Requires-Dist: requests
Requires-Dist: scikit-learn (>=1.0,<2.0)
Requires-Dist: scipy
Requires-Dist: tabulate
Requires-Dist: tqdm (>=4.61.2,<5.0.0)
